shinywidgets/__init__.py
shinywidgets/_as_widget.py
shinywidgets/_cdn.py
shinywidgets/_comm.py
shinywidgets/_dependencies.py
shinywidgets/_output_widget.py
shinywidgets/_render_widget.py
shinywidgets/_render_widget_base.py
shinywidgets/_serialization.py
shinywidgets/_shinywidgets.py
shinywidgets/_utils.py
shinywidgets/py.typed
shinywidgets/static/1e59d2330b4c6deb84b340635ed36249.ttf
shinywidgets/static/20fd1704ea223900efa9fd4e869efb08.woff2
shinywidgets/static/8b43027f47b20503057dfbbaa9401fef.eot
shinywidgets/static/c1e38fd9e0e74ba58f7a2b77ef29fdd3.svg
shinywidgets/static/f691f37e57f04c152e2315ab7dbad881.woff
shinywidgets/static/libembed-amd.js
shinywidgets/static/node_modules_codemirror_mode_sync_recursive_js_.output.js
shinywidgets/static/output.js
shinywidgets/static/shinywidgets.css
shinywidgets/static/vendors-node_modules_codemirror_mode_apl_apl_js-node_modules_codemirror_mode_asciiarmor_ascii-26282f.output.js
shinywidgets-0.7.1.dist-info/licenses/LICENSE
shinywidgets-0.7.1.dist-info/METADATA
shinywidgets-0.7.1.dist-info/WHEEL
shinywidgets-0.7.1.dist-info/top_level.txt
shinywidgets-0.7.1.dist-info/RECORD
