Metadata-Version: 2.4
Name: shinywidgets
Version: 0.7.1
Summary: Render ipywidgets in Shiny applications
Home-page: https://github.com/rstudio/py-shinywidgets
Author: Carson Sievert
Author-email: carson@rstudio.com
License: MIT
Project-URL: Bug Tracker, https://github.com/rstudio/py-shinywidgets/issues
Project-URL: Documentation, https://github.com/rstudio/py-shinywidgets/
Project-URL: Source Code, https://github.com/rstudio/py-shinywidgets/
Platform: any
Classifier: Development Status :: 2 - Pre-Alpha
Classifier: Intended Audience :: Developers
Classifier: License :: OSI Approved :: MIT License
Classifier: Natural Language :: English
Classifier: Programming Language :: Python :: 3.10
Classifier: Programming Language :: Python :: 3.11
Classifier: Programming Language :: Python :: 3.12
Classifier: Programming Language :: Python :: 3.13
Classifier: Programming Language :: Python :: 3.14
Requires-Python: >=3.10
License-File: LICENSE
Requires-Dist: ipywidgets>=7.6.5
Requires-Dist: jupyter_core
Requires-Dist: shiny>=0.6.1.9005
Requires-Dist: python-dateutil>=2.8.2
Requires-Dist: anywidget
Provides-Extra: test
Requires-Dist: pytest>=6.2.4; extra == "test"
Provides-Extra: dev
Requires-Dist: black>=23.1.0; extra == "dev"
Requires-Dist: flake8>=6.0.0; extra == "dev"
Requires-Dist: isort>=5.11.2; extra == "dev"
Requires-Dist: pyright>=1.1.284; extra == "dev"
Requires-Dist: wheel; extra == "dev"
Requires-Dist: altair; extra == "dev"
Requires-Dist: bokeh; extra == "dev"
Requires-Dist: jupyter_bokeh; extra == "dev"
Requires-Dist: plotly; extra == "dev"
Requires-Dist: pydeck; extra == "dev"
Dynamic: license-file
